quipu/__init__.py
quipu/interfaces/exceptions.py
quipu/interfaces/exceptions.stitcher.yaml
quipu/interfaces/models.py
quipu/interfaces/models.stitcher.yaml
quipu/interfaces/result.py
quipu/interfaces/result.stitcher.yaml
quipu/interfaces/storage.py
quipu/interfaces/storage.stitcher.yaml
quipu/interfaces/types.py
quipu/interfaces/types.stitcher.yaml
pyquipu_interfaces-0.1.1.dist-info/METADATA
pyquipu_interfaces-0.1.1.dist-info/WHEEL
pyquipu_interfaces-0.1.1.dist-info/RECORD
