Metadata-Version: 2.4
Name: pyquipu-interfaces
Version: 0.1.1
Summary: Core interfaces and data models for the Quipu ecosystem.
Project-URL: Homepage, https://github.com/quipu-dev/Quipu
Project-URL: Repository, https://github.com/quipu-dev/Quipu
Project-URL: Bug Tracker, https://github.com/quipu-dev/Quipu/issues
Author-email: doucx <doucxldh@gmail.com>
License-Expression: Apache-2.0
Keywords: api,devops,interfaces,models,quipu
Classifier: Development Status :: 3 - Alpha
Classifier: Intended Audience :: Developers
Classifier: License :: OSI Approved :: Apache Software License
Classifier: Operating System :: OS Independent
Classifier: Programming Language :: Python :: 3
Classifier: Programming Language :: Python :: 3.10
Classifier: Programming Language :: Python :: 3.11
Classifier: Topic :: Software Development :: Libraries :: Python Modules
Classifier: Typing :: Typed
Requires-Python: >=3.10
